stactools/goes/__init__.py
stactools/goes/attributes.py
stactools/goes/bands.py
stactools/goes/cog.py
stactools/goes/commands.py
stactools/goes/dataset.py
stactools/goes/enums.py
stactools/goes/errors.py
stactools/goes/file_name.py
stactools/goes/product.py
stactools/goes/stac.py
stactools/goes/utils.py
stactools_goes-0.1.8.dist-info/licenses/LICENSE
stactools_goes-0.1.8.dist-info/METADATA
stactools_goes-0.1.8.dist-info/WHEEL
stactools_goes-0.1.8.dist-info/top_level.txt
stactools_goes-0.1.8.dist-info/RECORD
