Metadata-Version: 2.4
Name: stactools-goes
Version: 0.1.8
Summary: stactools package for working with NOAA''s GOES data
Home-page: https://github.com/stactools-packages/goes
Author: stac-utils
Author-email: stac@radiant.earth
Project-URL: Documentation, https://stactools-goes.readthedocs.io/en/latest/
Project-URL: Issues, https://github.com/stactools-packages/goes/issues
Keywords: stactools,pystac,catalog,STAC
Classifier: Development Status :: 4 - Beta
Classifier: License :: OSI Approved :: Apache Software License
Classifier: Programming Language :: Python :: 3.8
Classifier: Programming Language :: Python :: 3.9
Classifier: Programming Language :: Python :: 3.10
Classifier: Programming Language :: Python :: 3.11
Classifier: Programming Language :: Python :: 3.12
License-File: LICENSE
Requires-Dist: stactools>=0.3.1
Requires-Dist: h5py>=3.1
Dynamic: license-file
